guru_pk_mcp/__init__.py
guru_pk_mcp/__main__.py
guru_pk_mcp/ab_testing.py
guru_pk_mcp/batch_prompts.py
guru_pk_mcp/config.py
guru_pk_mcp/dynamic_experts.py
guru_pk_mcp/mode_selector.py
guru_pk_mcp/models.py
guru_pk_mcp/personas.py
guru_pk_mcp/quality_monitor.py
guru_pk_mcp/server.py
guru_pk_mcp/session_manager.py
guru_pk_mcp/templates/__init__.py
guru_pk_mcp/templates/infographic_spa_prompt.md
guru_pk_mcp-1.2.4.dist-info/METADATA
guru_pk_mcp-1.2.4.dist-info/WHEEL
guru_pk_mcp-1.2.4.dist-info/entry_points.txt
guru_pk_mcp-1.2.4.dist-info/licenses/LICENSE
guru_pk_mcp-1.2.4.dist-info/RECORD
