Metadata-Version: 2.4
Name: guru-pk-mcp
Version: 1.2.4
Summary: MCP server enabling AI expert debates - Dynamic expert generation for personalized multi-round philosophical discussions on any topic
Project-URL: Homepage, https://github.com/MitsudoAI/guru-pk-mcp
Project-URL: Repository, https://github.com/MitsudoAI/guru-pk-mcp.git
Project-URL: Issues, https://github.com/MitsudoAI/guru-pk-mcp/issues
Project-URL: Documentation, https://github.com/MitsudoAI/guru-pk-mcp/blob/main/README.md
Project-URL: Changelog, https://github.com/MitsudoAI/guru-pk-mcp/releases
Project-URL: Source Code, https://github.com/MitsudoAI/guru-pk-mcp
Project-URL: Bug Tracker, https://github.com/MitsudoAI/guru-pk-mcp/issues
Author-email: Ryu <ryu@mitsudo.tech>
License: MIT License
License-File: LICENSE
Keywords: ai,claude-desktop,cursor,dynamic-experts,expert-debate,intelligent-generation,mcp,model-context-protocol,multi-round-debate,philosophy,uvx
Classifier: Development Status :: 4 - Beta
Classifier: Environment :: Console
Classifier: Framework :: AsyncIO
Classifier: Intended Audience :: Developers
Classifier: Intended Audience :: Education
Classifier: Intended Audience :: End Users/Desktop
Classifier: License :: OSI Approved :: MIT License
Classifier: Natural Language :: Chinese (Simplified)
Classifier: Natural Language :: English
Classifier: Operating System :: OS Independent
Classifier: Programming Language :: Python :: 3
Classifier: Programming Language :: Python :: 3.10
Classifier: Programming Language :: Python :: 3.11
Classifier: Programming Language :: Python :: 3.12
Classifier: Programming Language :: Python :: 3.13
Classifier: Topic :: Communications :: Chat
Classifier: Topic :: Education
Classifier: Topic :: Scientific/Engineering :: Artificial Intelligence
Classifier: Topic :: Text Processing :: Linguistic
Requires-Python: >=3.10
Requires-Dist: anyio>=4.0.0
Requires-Dist: mcp>=1.10.1
Requires-Dist: pydantic>=2.0.0
Provides-Extra: dev
Requires-Dist: black>=23.0.0; extra == 'dev'
Requires-Dist: isort>=5.12.0; extra == 'dev'
Requires-Dist: mypy>=1.0.0; extra == 'dev'
Requires-Dist: pre-commit>=3.0.0; extra == 'dev'
Requires-Dist: pytest-asyncio>=0.21.0; extra == 'dev'
Requires-Dist: pytest-cov>=4.0.0; extra == 'dev'
Requires-Dist: pytest>=7.0.0; extra == 'dev'
Requires-Dist: ruff>=0.1.0; extra == 'dev'
Provides-Extra: test
Requires-Dist: pytest-asyncio>=0.21.0; extra == 'test'
Requires-Dist: pytest-cov>=4.0.0; extra == 'test'
Requires-Dist: pytest-mock>=3.10.0; extra == 'test'
Requires-Dist: pytest>=7.0.0; extra == 'test'
